zelus/__init__.py
zelus/src/__init__.py
zelus/src/infrastructures/__init__.py
zelus/src/infrastructures/twitter/__init__.py
zelus/src/infrastructures/twitter/infrastructure.py
zelus/src/repositories/__init__.py
zelus/src/repositories/twitter/__init__.py
zelus/src/repositories/twitter/repository.py
zelus/src/services/__init__.py
zelus/src/services/twitter/__init__.py
zelus/src/services/twitter/service.py
zelus-0.1.0.dist-info/LICENSE
zelus-0.1.0.dist-info/WHEEL
zelus-0.1.0.dist-info/METADATA
zelus-0.1.0.dist-info/RECORD
