Metadata-Version: 2.1
Name: zelus
Version: 0.1.0
Summary: 
License: MIT
Author: João Pedro Jacques Hoss
Author-email: joaopedro_jh@hotmail.com
Requires-Python: >=3.8,<3.10
Classifier: License :: OSI Approved :: MIT License
Classifier: Programming Language :: Python :: 3
Classifier: Programming Language :: Python :: 3.8
Classifier: Programming Language :: Python :: 3.9
Requires-Dist: Flask (>=2.0.2,<3.0.0)
Requires-Dist: TwitterAPI (>=2.7.11,<3.0.0)
Requires-Dist: tweepy (>=4.4.0,<5.0.0)
